{
  "name": "miappio-sdk",
  "version": "1.0.79",
  "main": "dist/miapp.io.js",
  "ignore": [
    "**/.*",
    "*.sh",
    "src",
    "docs",
    "node_modules",
    "bower_components",
    "test",
    "Gruntfile.js"
  ],
  "dependencies": {
    "angular": ">=1.2.0"
  },
  "devDependencies": {},
  "homepage": "https://github.com/miappio/miappio-sdk",
  "authors": [
    "mlefree <mat@mlefree.com>"
  ],
  "description": "miapp.io client SDK",
  "keywords": [
    "miapp.io",
    "angular",
    "mobile",
    "integration"
  ],
  "license": "MIT",
  "_release": "1.0.79",
  "_resolution": {
    "type": "version",
    "tag": "v1.0.79",
    "commit": "9bd967f20d79571d83de8100996339ca20d1043c"
  },
  "_source": "https://github.com/miappio/miappio-sdk.git",
  "_target": "*",
  "_originalSource": "miappio-sdk"
}